Workbook

Sheet Sales_Data
A1: Global Tech Retailers - Sales Transactions Log
A3: Txn_ID | B3: Date | C3: Product_ID | D3: Region | E3: Sales_Rep | F3: Units_Sold | G3: Unit_Price | H3: Customer_Rating | I3: Product_Name (Task 5) | J3: Discount_Rate (Task 6)
A4: TXN-101 | B4: 2026-01-05 | C4: P-01 | D4: North | E4: Sarah | F4: 12 | G4: 1200 | H4: 5 | I4: =VLOOKUP(C4,Product_Catalog!$A$4:$D$9,3,FALSE) -> Laptop Pro | J4: =HLOOKUP(C4,Product_Catalog!$A$13:$F$14,2,FALSE) -> 0.1
A5: TXN-102 | B5: 2026-01-07 | C5: P-02 | D5: East | E5: Raj | F5: 5 | G5: 800 | H5: 4 | I5: =VLOOKUP(C5,Product_Catalog!$A$4:$D$9,3,FALSE) -> Tablet Air | J5: =HLOOKUP(C5,Product_Catalog!$A$13:$F$14,2,FALSE) -> 0.05
A6: TXN-103 | B6: 2026-01-10 | C6: P-03 | D6: North | E6: Sarah | G6: 150 | H6: 3 | I6: =VLOOKUP(C6,Product_Catalog!$A$4:$D$9,3,FALSE) -> Wireless Mouse | J6: =HLOOKUP(C6,Product_Catalog!$A$13:$F$14,2,FALSE) -> 0
A7: TXN-104 | B7: 2026-01-12 | C7: P-01 | D7: West | E7: Amit | F7: 8 | G7: 1200 | H7: 5 | I7: =VLOOKUP(C7,Product_Catalog!$A$4:$D$9,3,FALSE) -> Laptop Pro | J7: =HLOOKUP(C7,Product_Catalog!$A$13:$F$14,2,FALSE) -> 0.1
A8: TXN-105 | B8: 2026-01-15 | C8: P-04 | D8: South | E8: Priya | F8: 15 | G8: 45 | I8: =VLOOKUP(C8,Product_Catalog!$A$4:$D$9,3,FALSE) -> USB Cable | J8: =HLOOKUP(C8,Product_Catalog!$A$13:$F$14,2,FALSE) -> 0.02
A9: TXN-106 | B9: 2026-01-18 | C9: P-02 | D9: North | E9: Raj | F9: 2 | G9: 800 | H9: 2 | I9: =VLOOKUP(C9,Product_Catalog!$A$4:$D$9,3,FALSE) -> Tablet Air | J9: =HLOOKUP(C9,Product_Catalog!$A$13:$F$14,2,FALSE) -> 0.05
A10: TXN-107 | B10: 2026-01-20 | C10: P-05 | D10: West | E10: Amit | F10: 20 | H10: 4 | I10: =VLOOKUP(C10,Product_Catalog!$A$4:$D$9,3,FALSE) -> Ergonomic Chair | J10: =HLOOKUP(C10,Product_Catalog!$A$13:$F$14,2,FALSE) -> 0.15
A11: TXN-108 | B11: 2026-01-22 | C11: P-03 | D11: South | E11: Priya | F11: 10 | G11: 150 | H11: 5 | I11: =VLOOKUP(C11,Product_Catalog!$A$4:$D$9,3,FALSE) -> Wireless Mouse | J11: =HLOOKUP(C11,Product_Catalog!$A$13:$F$14,2,FALSE) -> 0
A12: TXN-109 | B12: 2026-01-25 | C12: P-01 | D12: East | E12: Sarah | F12: 4 | G12: 1200 | I12: =VLOOKUP(C12,Product_Catalog!$A$4:$D$9,3,FALSE) -> Laptop Pro | J12: =HLOOKUP(C12,Product_Catalog!$A$13:$F$14,2,FALSE) -> 0.1
A13: TXN-110 | B13: 2026-01-28 | C13: P-04 | D13: North | E13: Raj | F13: 0 | G13: 45 | H13: 1 | I13: =VLOOKUP(C13,Product_Catalog!$A$4:$D$9,3,FALSE) -> USB Cable | J13: =HLOOKUP(C13,Product_Catalog!$A$13:$F$14,2,FALSE) -> 0.02

Sheet Product_Catalog
A1: Product Reference Catalog & Discount Schedules
A3: Table A: Product Master Catalog (Vertical)
A4: Product_ID | B4: Category | C4: Product_Name | D4: Supplier
A5: P-01 | B5: Electronics | C5: Laptop Pro | D5: TechCorp
A6: P-02 | B6: Electronics | C6: Tablet Air | D6: PadMaker
A7: P-03 | B7: Accessories | C7: Wireless Mouse | D7: LogiGear
A8: P-04 | B8: Accessories | C8: USB Cable | D8: CableMax
A9: P-05 | B9: Office | C9: Ergonomic Chair | D9: ComfortPlus
A12: Table B: Volume Discount Matrix (Horizontal)
A13: Product_ID | B13: P-01 | C13: P-02 | D13: P-03 | E13: P-04 | F13: P-05
A14: Discount Rate | B14: 0.1 | C14: 0.05 | D14: 0 | E14: 0.02 | F14: 0.15

Sheet Assignment_Tasks
A1: Excel Aggregate & Lookup Function Practice Assignment
A3: Task ID | B3: Category / Topic | C3: Task Question / Objective | D3: Your Formula Here | E3: Expected Output
A4: Task 1A | B4: Counting Functions | C4: Count the total number of numeric entries in Units_Sold column. | D4: =COUNT(Sales_Data!F4:F13) -> 9 | E4: 9
A5: Task 1B | B5: Counting Functions | C5: Count total non-empty transactions in Txn_ID column. | D5: =COUNTA(Sales_Data!A4:A13) -> 10 | E5: 10
A6: Task 1C | B6: Counting Functions | C6: Count how many transactions have missing (blank) Customer_Rating. | D6: =COUNTBLANK(Sales_Data!H4:H13) -> 2 | E6: 2
A7: Task 2A | B7: Conditional Counting | C7: Count how many transactions were completed by sales rep 'Sarah'. | D7: =COUNTIF(Sales_Data!E4:E13,"Sarah") -> 3 | E7: 3
A8: Task 2B | B8: Conditional Counting | C8: Count transactions in 'North' region where Units_Sold is greater than 5. | D8: =COUNTIFS(Sales_Data!F4:F13,">=5",Sales_Data!D4:D13,"North") -> 1 | E8: 1
A9: Task 3A | B9: Aggregations & Math | C9: Calculate the overall average Units_Sold across all recorded sales. | D9: =AVERAGE(Sales_Data!F4:F13) -> 8.4444444 | E9: 8.22
A10: Task 3B | B10: Aggregations & Math | C10: Calculate total Units_Sold only for Product_ID 'P-01'. | D10: =SUMIFS(Sales_Data!F4:F13,Sales_Data!C4:C13,"P-01") -> 24 | E10: 24
A11: Task 3C | B11: Aggregations & Math | C11: Calculate total Units_Sold by 'Amit' in the 'West' region. | D11: =SUMIFS(Sales_Data!F4:F13,Sales_Data!E4:E13,"Amit",Sales_Data!D4:D13,"West") -> 28 | E11: 28
A12: Task 4A | B12: Target Averages | C12: Calculate average Customer_Rating for the 'North' region. | D12: =AVERAGEIF(Sales_Data!D4:D13,"North",Sales_Data!H4:H13) -> 2.75 | E12: 3
A13: Task 4B | B13: Target Averages | C13: Calculate average Units_Sold by 'Sarah' for transactions with Customer_Rating >= 4. | D13: =AVERAGEIFS(Sales_Data!F4:F13,Sales_Data!E4:E13,"Sarah",Sales_Data!H4:H13,">=4") -> 12 | E13: 8
A14: Task 5 | B14: Vertical Lookups | C14: Populate Product_Name in Sales_Data column I using VLOOKUP. | D14: =VLOOKUP(Sales_Data!C4,Product_Catalog!$A$4:$D$9,3,FALSE) -> Laptop Pro | E14: See Column I in Sales_Data
A15: Task 6 | B15: Horizontal Lookups | C15: Populate Discount_Rate in Sales_Data column J using HLOOKUP. | D15: =HLOOKUP(Sales_Data!C4,Product_Catalog!$A$13:$F$14,2,FALSE) -> 0.1 | E15: See Column J in Sales_Data
A16: Task 7 | B16: INDEX & MATCH | C16: Write a 2-way INDEX+MATCH to dynamically find Supplier for Product ID 'P-03'. | D16: =INDEX(Product_Catalog!D5:D9,MATCH("P-03",Product_Catalog!A5:A9,0)) -> LogiGear | E16: LogiGear
A17: Task 8 | B17: Reverse INDEX & MATCH | C17: Look up Product_ID where Product_Name is 'Ergonomic Chair' (Left Lookup). | D17: =INDEX(Product_Catalog!A5:A9,MATCH("Ergonomic Chair",Product_Catalog!C5:C9,0)) -> P-05 | E17: P-05
A18: Task 9A | B18: Advanced Aggregations | C18: Calculate total sales revenue (Units_Sold * Unit_Price) for the 'North' region only. | D18: =SUMPRODUCT((Sales_Data!D4:D13="North")*Sales_Data!F4:F13*Sales_Data!G4:G13) -> 16000 | E18: $15,390
A19: Task 9B | B19: Advanced Aggregations | C19: Calculate the average Customer_Rating ignoring all blank ratings and ratings equal to 1. | D19: =AVERAGEIFS(Sales_Data!H4:H13,Sales_Data!H4:H13,">1") -> 4 | E19: 4.25
A20: Task 10A | B20: Dynamic Lookups | C20: Use INDEX + MATCH to find the Sales Rep who made the single highest unit sale. | D20: =INDEX(Sales_Data!E4:E13,MATCH(MAX(Sales_Data!F4:F13),Sales_Data!F4:F13,0)) -> Amit | E20: Amit
A21: Task 10B | B21: Dynamic Lookups | C21: Use INDEX + MATCH to find the Date of transaction 'TXN-108'. | D21: =INDEX(Sales_Data!B4:B13,MATCH("TXN-108",Sales_Data!A4:A13,0)) -> 2026-01-22 | E21: 2026-01-22
A22: Task 11A | B22: Error Handling & Logic | C22: Write a formula using IF + ISBLANK to return 'Incomplete' if Units_Sold is blank, else 'Complete' for row TXN-103. | D22: =IF(ISBLANK(INDEX(Sales_Data!F4:F13,MATCH("TXN-103",Sales_Data!A4:A13,0))),"Incomplete","Complete") -> Incomplete | E22: Incomplete
A23: Task 11B | B23: Error Handling & Logic | C23: Write a VLOOKUP wrapped in IFERROR to look up Product ID 'P-99' (which doesn't exist) and return 'Not Found'. | D23: =IFERROR(VLOOKUP("P-99",Sales_Data!A3:H13,3,FALSE),"Not Found") -> Not Found | E23: Not Found
